illumo_flow/__init__.py
illumo_flow/core.py
illumo_flow-0.1.4.dist-info/METADATA
illumo_flow-0.1.4.dist-info/WHEEL
illumo_flow-0.1.4.dist-info/top_level.txt
illumo_flow-0.1.4.dist-info/RECORD
