Metadata-Version: 2.4
Name: illumo-flow
Version: 0.1.4
Summary: Workflow orchestration primitives for illumo demo
Requires-Python: >=3.10
Requires-Dist: PyYAML>=6
